typelate/__init__.py
typelate/_parsing_error.py
typelate/_specifier_deleter.py
typelate/_template.py
typelate-0.1.0.dist-info/LICENSE
typelate-0.1.0.dist-info/METADATA
typelate-0.1.0.dist-info/WHEEL
typelate-0.1.0.dist-info/top_level.txt
typelate-0.1.0.dist-info/RECORD
