Metadata-Version: 2.1
Name: typelate
Version: 0.1.0
Summary: Python templates with type annotations and validation.
Author: Ariel Alon
License: Copyright © 2024 ArielAlon24
Project-URL: Homepage, https://github.com/ArielAlon24/typed-template
Classifier: Programming Language :: Python :: 3
Classifier: License :: OSI Approved :: MIT License
Classifier: Operating System :: OS Independent
Requires-Python: >=3.8
License-File: LICENSE
Requires-Dist: iniconfig >=2.0.0
Requires-Dist: packaging >=23.2
Requires-Dist: pluggy >=1.4.0
Requires-Dist: typeguard >=4.1.5
Requires-Dist: typing-extensions >=4.10.0
